{"daily": {"2025-01-01": {"accommodations_booked": 72, "revenue": 3207.890000000001}, "2025-01-02": {"accommodations_booked": 66, "revenue": 2739.0700000000006}, "2025-01-03": {"accommodations_booked": 63, "revenue": 2565.2200000000007}, "2025-01-04": {"accommodations_booked": 70, "revenue": 2853.64}, "2025-01-05": {"accommodations_booked": 70, "revenue": 2783.590000000001}, "2025-01-06": {"accommodations_booked": 71, "revenue": 3005.0700000000006}, "2025-01-07": {"accommodations_booked": 66, "revenue": 2908.0100000000007}, "2025-01-08": {"accommodations_booked": 68, "revenue": 2781.55}, "2025-01-09": {"accommodations_booked": 69, "revenue": 2903.6000000000004}, "2025-01-10": {"accommodations_booked": 73, "revenue": 3195.7299999999996}, "2025-01-11": {"accommodations_booked": 72, "revenue": 3267.729999999998}, "2025-01-12": {"accommodations_booked": 70, "revenue": 2750.4600000000005}, "2025-01-13": {"accommodations_booked": 81, "revenue": 3085.3400000000006}, "2025-01-14": {"accommodations_booked": 81, "revenue": 3085.0599999999995}, "2025-01-15": {"accommodations_booked": 83, "revenue": 3134.73}, "2025-01-16": {"accommodations_booked": 83, "revenue": 3277.000000000001}, "2025-01-17": {"accommodations_booked": 83, "revenue": 3330.839999999999}, "2025-01-18": {"accommodations_booked": 82, "revenue": 3393.9099999999985}, "2025-01-19": {"accommodations_booked": 80, "revenue": 3002.8799999999997}, "2025-01-20": {"accommodations_booked": 78, "revenue": 2708.5900000000006}, "2025-01-21": {"accommodations_booked": 76, "revenue": 2573.88}, "2025-01-22": {"accommodations_booked": 77, "revenue": 2629.8399999999992}, "2025-01-23": {"accommodations_booked": 75, "revenue": 2677.0700000000006}, "2025-01-24": {"accommodations_booked": 75, "revenue": 2764.2900000000004}, "2025-01-25": {"accommodations_booked": 76, "revenue": 2796.47}, "2025-01-26": {"accommodations_booked": 74, "revenue": 2620.590000000001}, "2025-01-27": {"accommodations_booked": 72, "revenue": 2545.330000000001}, "2025-01-28": {"accommodations_booked": 64, "revenue": 2212.930000000001}, "2025-01-29": {"accommodations_booked": 63, "revenue": 2119.05}, "2025-01-30": {"accommodations_booked": 67, "revenue": 2293.320000000001}, "2025-01-31": {"accommodations_booked": 69, "revenue": 2330.1800000000007}, "2025-02-01": {"accommodations_booked": 73, "revenue": 2500.5500000000006}, "2025-02-02": {"accommodations_booked": 74, "revenue": 2486.8200000000006}, "2025-02-03": {"accommodations_booked": 73, "revenue": 2363.29}, "2025-02-04": {"accommodations_booked": 81, "revenue": 2633.170000000001}, "2025-02-05": {"accommodations_booked": 80, "revenue": 2732.36}, "2025-02-06": {"accommodations_booked": 76, "revenue": 2455.030000000001}, "2025-02-07": {"accommodations_booked": 86, "revenue": 3165.300000000001}, "2025-02-08": {"accommodations_booked": 87, "revenue": 3071.7799999999997}, "2025-02-09": {"accommodations_booked": 83, "revenue": 2788.1699999999996}, "2025-02-10": {"accommodations_booked": 79, "revenue": 2629.3}, "2025-02-11": {"accommodations_booked": 73, "revenue": 2394.7800000000007}, "2025-02-12": {"accommodations_booked": 74, "revenue": 2663.089999999999}, "2025-02-13": {"accommodations_booked": 80, "revenue": 2917.899999999999}, "2025-02-14": {"accommodations_booked": 83, "revenue": 3142.179999999999}, "2025-02-15": {"accommodations_booked": 91, "revenue": 3360.4600000000005}, "2025-02-16": {"accommodations_booked": 83, "revenue": 2797.1800000000003}, "2025-02-17": {"accommodations_booked": 76, "revenue": 2435.9700000000003}, "2025-02-18": {"accommodations_booked": 73, "revenue": 2363.960000000001}, "2025-02-19": {"accommodations_booked": 74, "revenue": 2398.2299999999996}, "2025-02-20": {"accommodations_booked": 75, "revenue": 2495.05}, "2025-02-21": {"accommodations_booked": 91, "revenue": 3963.3999999999996}, "2025-02-22": {"accommodations_booked": 92, "revenue": 4075.9399999999973}, "2025-02-23": {"accommodations_booked": 91, "revenue": 3898.4399999999987}, "2025-02-24": {"accommodations_booked": 91, "revenue": 3952.2399999999984}, "2025-02-25": {"accommodations_booked": 66, "revenue": 2135.4900000000007}, "2025-02-26": {"accommodations_booked": 76, "revenue": 2509.0900000000015}, "2025-02-27": {"accommodations_booked": 87, "revenue": 3191.4800000000023}, "2025-02-28": {"accommodations_booked": 90, "revenue": 3400.41}, "2025-03-01": {"accommodations_booked": 93, "revenue": 3532.780000000001}, "2025-03-02": {"accommodations_booked": 89, "revenue": 3216.27}, "2025-03-03": {"accommodations_booked": 87, "revenue": 3114.4700000000007}, "2025-03-04": {"accommodations_booked": 90, "revenue": 3169.75}, "2025-03-05": {"accommodations_booked": 91, "revenue": 3271.620000000001}, "2025-03-06": {"accommodations_booked": 92, "revenue": 3237.030000000001}, "2025-03-07": {"accommodations_booked": 92, "revenue": 3349.27}, "2025-03-08": {"accommodations_booked": 93, "revenue": 3591.8300000000004}, "2025-03-09": {"accommodations_booked": 92, "revenue": 3350.2200000000007}, "2025-03-10": {"accommodations_booked": 93, "revenue": 3449.8400000000006}, "2025-03-11": {"accommodations_booked": 81, "revenue": 2935.0}, "2025-03-12": {"accommodations_booked": 92, "revenue": 3769.239999999999}, "2025-03-13": {"accommodations_booked": 83, "revenue": 8205.149999999996}, "2025-03-14": {"accommodations_booked": 92, "revenue": 9238.530000000002}, "2025-03-15": {"accommodations_booked": 90, "revenue": 9507.170000000002}, "2025-03-16": {"accommodations_booked": 70, "revenue": 6654.030000000001}, "2025-03-17": {"accommodations_booked": 76, "revenue": 2813.63}, "2025-03-18": {"accommodations_booked": 73, "revenue": 2650.47}, "2025-03-19": {"accommodations_booked": 74, "revenue": 2630.2900000000013}, "2025-03-20": {"accommodations_booked": 75, "revenue": 2614.1500000000005}, "2025-03-21": {"accommodations_booked": 83, "revenue": 3091.110000000001}, "2025-03-22": {"accommodations_booked": 85, "revenue": 3115.4899999999984}, "2025-03-23": {"accommodations_booked": 76, "revenue": 2733.040000000001}, "2025-03-24": {"accommodations_booked": 63, "revenue": 2109.4400000000014}, "2025-03-25": {"accommodations_booked": 68, "revenue": 2303.610000000001}, "2025-03-26": {"accommodations_booked": 69, "revenue": 2243.500000000001}, "2025-03-27": {"accommodations_booked": 81, "revenue": 2888.260000000001}, "2025-03-28": {"accommodations_booked": 83, "revenue": 2957.4300000000003}, "2025-03-29": {"accommodations_booked": 87, "revenue": 3182.480000000001}, "2025-03-30": {"accommodations_booked": 81, "revenue": 2704.5399999999995}, "2025-03-31": {"accommodations_booked": 65, "revenue": 2113.61}, "2025-04-01": {"accommodations_booked": 61, "revenue": 1909.1900000000012}, "2025-04-02": {"accommodations_booked": 65, "revenue": 2042.0400000000006}, "2025-04-03": {"accommodations_booked": 64, "revenue": 2069.1000000000004}, "2025-04-04": {"accommodations_booked": 67, "revenue": 2173.0400000000004}, "2025-04-05": {"accommodations_booked": 71, "revenue": 2301.8}, "2025-04-06": {"accommodations_booked": 70, "revenue": 2213.82}, "2025-04-07": {"accommodations_booked": 66, "revenue": 2045.5899999999997}, "2025-04-08": {"accommodations_booked": 64, "revenue": 2053.33}, "2025-04-09": {"accommodations_booked": 63, "revenue": 2023.7900000000002}, "2025-04-10": {"accommodations_booked": 54, "revenue": 1835.7300000000002}, "2025-04-11": {"accommodations_booked": 55, "revenue": 1800.5800000000002}, "2025-04-12": {"accommodations_booked": 60, "revenue": 2123.72}, "2025-04-13": {"accommodations_booked": 56, "revenue": 1891.7900000000004}, "2025-04-14": {"accommodations_booked": 59, "revenue": 1960.8700000000008}, "2025-04-15": {"accommodations_booked": 56, "revenue": 1859.3500000000001}, "2025-04-16": {"accommodations_booked": 58, "revenue": 1903.2300000000007}, "2025-04-17": {"accommodations_booked": 64, "revenue": 2089.92}, "2025-04-18": {"accommodations_booked": 66, "revenue": 2275.219999999999}, "2025-04-19": {"accommodations_booked": 66, "revenue": 2408.2500000000005}, "2025-04-20": {"accommodations_booked": 62, "revenue": 2098.37}, "2025-04-21": {"accommodations_booked": 54, "revenue": 1882.7699999999998}, "2025-04-22": {"accommodations_booked": 54, "revenue": 1801.0100000000007}, "2025-04-23": {"accommodations_booked": 57, "revenue": 1964.8500000000006}, "2025-04-24": {"accommodations_booked": 51, "revenue": 1770.7000000000005}, "2025-04-25": {"accommodations_booked": 50, "revenue": 1729.9000000000003}, "2025-04-26": {"accommodations_booked": 48, "revenue": 1709.46}, "2025-04-27": {"accommodations_booked": 44, "revenue": 1467.7100000000003}, "2025-04-28": {"accommodations_booked": 48, "revenue": 1569.5900000000001}, "2025-04-29": {"accommodations_booked": 44, "revenue": 1442.39}, "2025-04-30": {"accommodations_booked": 42, "revenue": 1381.07}, "2025-05-01": {"accommodations_booked": 41, "revenue": 1430.4500000000003}, "2025-05-02": {"accommodations_booked": 43, "revenue": 1432.9499999999998}, "2025-05-03": {"accommodations_booked": 47, "revenue": 1572.96}, "2025-05-04": {"accommodations_booked": 40, "revenue": 1369.96}, "2025-05-05": {"accommodations_booked": 39, "revenue": 1370.6399999999999}, "2025-05-06": {"accommodations_booked": 36, "revenue": 1313.3899999999999}, "2025-05-07": {"accommodations_booked": 38, "revenue": 1376.9699999999998}, "2025-05-08": {"accommodations_booked": 40, "revenue": 1403.2800000000002}, "2025-05-09": {"accommodations_booked": 40, "revenue": 1374.9199999999998}, "2025-05-10": {"accommodations_booked": 34, "revenue": 1214.8500000000001}, "2025-05-11": {"accommodations_booked": 33, "revenue": 1133.2300000000002}, "2025-05-12": {"accommodations_booked": 32, "revenue": 1072.1100000000001}, "2025-05-13": {"accommodations_booked": 33, "revenue": 1203.3600000000001}, "2025-05-14": {"accommodations_booked": 33, "revenue": 1171.3799999999999}, "2025-05-15": {"accommodations_booked": 31, "revenue": 1069.4699999999998}, "2025-05-16": {"accommodations_booked": 31, "revenue": 1120.93}, "2025-05-17": {"accommodations_booked": 33, "revenue": 995.88}, "2025-05-18": {"accommodations_booked": 31, "revenue": 1141.1799999999998}, "2025-05-19": {"accommodations_booked": 33, "revenue": 1116.75}, "2025-05-20": {"accommodations_booked": 35, "revenue": 1164.3000000000002}, "2025-05-21": {"accommodations_booked": 36, "revenue": 1268.1499999999996}, "2025-05-22": {"accommodations_booked": 34, "revenue": 1204.69}, "2025-05-23": {"accommodations_booked": 37, "revenue": 1366.6999999999998}, "2025-05-24": {"accommodations_booked": 37, "revenue": 1505.6200000000003}, "2025-05-25": {"accommodations_booked": 34, "revenue": 1222.0}, "2025-05-26": {"accommodations_booked": 33, "revenue": 1060.72}, "2025-05-27": {"accommodations_booked": 34, "revenue": 1068.4599999999998}, "2025-05-28": {"accommodations_booked": 35, "revenue": 1214.9800000000002}, "2025-05-29": {"accommodations_booked": 36, "revenue": 1291.16}, "2025-05-30": {"accommodations_booked": 36, "revenue": 1340.0400000000002}, "2025-05-31": {"accommodations_booked": 39, "revenue": 1489.8899999999999}, "2025-06-01": {"accommodations_booked": 36, "revenue": 1331.91}, "2025-06-02": {"accommodations_booked": 30, "revenue": 985.4000000000003}, "2025-06-03": {"accommodations_booked": 29, "revenue": 941.4399999999999}, "2025-06-04": {"accommodations_booked": 29, "revenue": 948.8}, "2025-06-05": {"accommodations_booked": 26, "revenue": 862.8800000000002}, "2025-06-06": {"accommodations_booked": 27, "revenue": 1065.96}, "2025-06-07": {"accommodations_booked": 27, "revenue": 1113.7400000000002}, "2025-06-08": {"accommodations_booked": 23, "revenue": 894.02}, "2025-06-09": {"accommodations_booked": 20, "revenue": 642.92}, "2025-06-10": {"accommodations_booked": 19, "revenue": 567.24}, "2025-06-11": {"accommodations_booked": 19, "revenue": 567.27}, "2025-06-12": {"accommodations_booked": 21, "revenue": 683.58}, "2025-06-13": {"accommodations_booked": 25, "revenue": 876.41}, "2025-06-14": {"accommodations_booked": 25, "revenue": 850.5600000000002}, "2025-06-15": {"accommodations_booked": 24, "revenue": 775.6100000000001}, "2025-06-16": {"accommodations_booked": 28, "revenue": 1247.7700000000004}, "2025-06-17": {"accommodations_booked": 28, "revenue": 956.8900000000001}, "2025-06-18": {"accommodations_booked": 30, "revenue": 1010.5200000000001}, "2025-06-19": {"accommodations_booked": 29, "revenue": 974.8200000000002}, "2025-06-20": {"accommodations_booked": 34, "revenue": 1244.17}, "2025-06-21": {"accommodations_booked": 35, "revenue": 1231.6100000000001}, "2025-06-22": {"accommodations_booked": 32, "revenue": 1079.23}, "2025-06-23": {"accommodations_booked": 32, "revenue": 1184.1000000000001}, "2025-06-24": {"accommodations_booked": 32, "revenue": 1158.1800000000003}, "2025-06-25": {"accommodations_booked": 31, "revenue": 1034.8600000000004}, "2025-06-26": {"accommodations_booked": 36, "revenue": 1334.6}, "2025-06-27": {"accommodations_booked": 33, "revenue": 1186.6699999999998}, "2025-06-28": {"accommodations_booked": 34, "revenue": 1314.7800000000002}, "2025-06-29": {"accommodations_booked": 31, "revenue": 1125.9800000000002}, "2025-06-30": {"accommodations_booked": 24, "revenue": 937.2400000000002}, "2025-07-01": {"accommodations_booked": 25, "revenue": 1030.6299999999999}, "2025-07-02": {"accommodations_booked": 24, "revenue": 897.51}, "2025-07-03": {"accommodations_booked": 25, "revenue": 1036.9500000000003}, "2025-07-04": {"accommodations_booked": 28, "revenue": 1166.53}, "2025-07-05": {"accommodations_booked": 36, "revenue": 1445.89}, "2025-07-06": {"accommodations_booked": 27, "revenue": 1124.57}, "2025-07-07": {"accommodations_booked": 28, "revenue": 1103.3899999999999}, "2025-07-08": {"accommodations_booked": 24, "revenue": 928.5599999999997}, "2025-07-09": {"accommodations_booked": 25, "revenue": 1019.5300000000002}, "2025-07-10": {"accommodations_booked": 29, "revenue": 1124.0700000000002}, "2025-07-11": {"accommodations_booked": 36, "revenue": 1389.2700000000002}, "2025-07-12": {"accommodations_booked": 34, "revenue": 1318.5399999999997}, "2025-07-13": {"accommodations_booked": 26, "revenue": 1020.1400000000003}, "2025-07-14": {"accommodations_booked": 25, "revenue": 965.4800000000001}, "2025-07-15": {"accommodations_booked": 26, "revenue": 1011.76}, "2025-07-16": {"accommodations_booked": 27, "revenue": 1106.27}, "2025-07-17": {"accommodations_booked": 29, "revenue": 1166.13}, "2025-07-18": {"accommodations_booked": 31, "revenue": 1205.8700000000001}, "2025-07-19": {"accommodations_booked": 34, "revenue": 1327.1299999999999}, "2025-07-20": {"accommodations_booked": 33, "revenue": 1344.35}, "2025-07-21": {"accommodations_booked": 32, "revenue": 1194.8200000000002}, "2025-07-22": {"accommodations_booked": 32, "revenue": 1229.8799999999999}, "2025-07-23": {"accommodations_booked": 31, "revenue": 1142.97}, "2025-07-24": {"accommodations_booked": 33, "revenue": 1232.7299999999998}, "2025-07-25": {"accommodations_booked": 37, "revenue": 1356.8299999999995}, "2025-07-26": {"accommodations_booked": 42, "revenue": 1906.2199999999998}, "2025-07-27": {"accommodations_booked": 32, "revenue": 1193.5599999999997}, "2025-07-28": {"accommodations_booked": 32, "revenue": 1124.01}, "2025-07-29": {"accommodations_booked": 30, "revenue": 1185.1299999999999}, "2025-07-30": {"accommodations_booked": 29, "revenue": 1034.2900000000002}, "2025-07-31": {"accommodations_booked": 33, "revenue": 1263.3}, "2025-08-01": {"accommodations_booked": 34, "revenue": 1283.8}, "2025-08-02": {"accommodations_booked": 35, "revenue": 1313.7399999999998}, "2025-08-03": {"accommodations_booked": 30, "revenue": 1157.77}, "2025-08-04": {"accommodations_booked": 28, "revenue": 1063.7700000000002}, "2025-08-05": {"accommodations_booked": 30, "revenue": 1097.58}, "2025-08-06": {"accommodations_booked": 30, "revenue": 1068.9299999999998}, "2025-08-07": {"accommodations_booked": 30, "revenue": 1139.4300000000003}, "2025-08-08": {"accommodations_booked": 32, "revenue": 1228.3199999999997}, "2025-08-09": {"accommodations_booked": 32, "revenue": 1156.75}, "2025-08-10": {"accommodations_booked": 26, "revenue": 950.0899999999999}, "2025-08-11": {"accommodations_booked": 24, "revenue": 807.3399999999999}, "2025-08-12": {"accommodations_booked": 27, "revenue": 964.5500000000001}, "2025-08-13": {"accommodations_booked": 25, "revenue": 934.4199999999998}, "2025-08-14": {"accommodations_booked": 31, "revenue": 1126.23}, "2025-08-15": {"accommodations_booked": 31, "revenue": 1208.9699999999998}, "2025-08-16": {"accommodations_booked": 32, "revenue": 1251.54}, "2025-08-17": {"accommodations_booked": 29, "revenue": 1166.75}, "2025-08-18": {"accommodations_booked": 27, "revenue": 996.0799999999999}, "2025-08-19": {"accommodations_booked": 26, "revenue": 1016.4199999999997}, "2025-08-20": {"accommodations_booked": 28, "revenue": 1053.13}, "2025-08-21": {"accommodations_booked": 32, "revenue": 1169.8399999999997}, "2025-08-22": {"accommodations_booked": 29, "revenue": 1076.0099999999998}, "2025-08-23": {"accommodations_booked": 30, "revenue": 1098.1299999999999}, "2025-08-24": {"accommodations_booked": 29, "revenue": 1028.09}, "2025-08-25": {"accommodations_booked": 26, "revenue": 905.3599999999999}, "2025-08-26": {"accommodations_booked": 26, "revenue": 941.7}, "2025-08-27": {"accommodations_booked": 26, "revenue": 925.8}, "2025-08-28": {"accommodations_booked": 26, "revenue": 918.18}, "2025-08-29": {"accommodations_booked": 25, "revenue": 801.77}, "2025-08-30": {"accommodations_booked": 25, "revenue": 931.12}, "2025-08-31": {"accommodations_booked": 26, "revenue": 950.9899999999998}, "2025-09-01": {"accommodations_booked": 23, "revenue": 806.6099999999999}, "2025-09-02": {"accommodations_booked": 26, "revenue": 1009.68}, "2025-09-03": {"accommodations_booked": 27, "revenue": 1041.1699999999998}, "2025-09-04": {"accommodations_booked": 28, "revenue": 1057.28}, "2025-09-05": {"accommodations_booked": 32, "revenue": 1240.14}, "2025-09-06": {"accommodations_booked": 31, "revenue": 1215.04}, "2025-09-07": {"accommodations_booked": 29, "revenue": 1145.2599999999995}, "2025-09-08": {"accommodations_booked": 28, "revenue": 1078.0599999999997}, "2025-09-09": {"accommodations_booked": 30, "revenue": 1140.4099999999999}, "2025-09-10": {"accommodations_booked": 29, "revenue": 1065.91}, "2025-09-11": {"accommodations_booked": 28, "revenue": 1112.87}, "2025-09-12": {"accommodations_booked": 29, "revenue": 1151.27}, "2025-09-13": {"accommodations_booked": 28, "revenue": 1153.9199999999998}, "2025-09-14": {"accommodations_booked": 27, "revenue": 1127.8200000000002}, "2025-09-15": {"accommodations_booked": 26, "revenue": 1004.2599999999999}, "2025-09-16": {"accommodations_booked": 28, "revenue": 934.5000000000001}, "2025-09-17": {"accommodations_booked": 30, "revenue": 1048.6699999999998}, "2025-09-18": {"accommodations_booked": 29, "revenue": 1011.2099999999998}, "2025-09-19": {"accommodations_booked": 29, "revenue": 1028.4899999999998}, "2025-09-20": {"accommodations_booked": 34, "revenue": 1331.9299999999998}, "2025-09-21": {"accommodations_booked": 34, "revenue": 1292.6899999999998}, "2025-09-22": {"accommodations_booked": 30, "revenue": 1060.8300000000002}, "2025-09-23": {"accommodations_booked": 32, "revenue": 1150.89}, "2025-09-24": {"accommodations_booked": 33, "revenue": 1222.0700000000002}, "2025-09-25": {"accommodations_booked": 34, "revenue": 1270.8099999999997}, "2025-09-26": {"accommodations_booked": 45, "revenue": 1659.7899999999997}, "2025-09-27": {"accommodations_booked": 48, "revenue": 1797.0299999999997}, "2025-09-28": {"accommodations_booked": 39, "revenue": 1523.3499999999997}, "2025-09-29": {"accommodations_booked": 34, "revenue": 1273.0199999999998}, "2025-09-30": {"accommodations_booked": 34, "revenue": 1311.2599999999995}, "2025-10-01": {"accommodations_booked": 37, "revenue": 1422.3000000000002}, "2025-10-02": {"accommodations_booked": 34, "revenue": 1234.2799999999997}, "2025-10-03": {"accommodations_booked": 41, "revenue": 1550.7599999999998}, "2025-10-04": {"accommodations_booked": 42, "revenue": 1598.6299999999997}, "2025-10-05": {"accommodations_booked": 39, "revenue": 1452.0300000000002}, "2025-10-06": {"accommodations_booked": 40, "revenue": 1434.6399999999999}, "2025-10-07": {"accommodations_booked": 38, "revenue": 1381.9099999999996}, "2025-10-08": {"accommodations_booked": 40, "revenue": 1545.2599999999998}, "2025-10-09": {"accommodations_booked": 39, "revenue": 1494.7499999999995}, "2025-10-10": {"accommodations_booked": 54, "revenue": 1983.29}, "2025-10-11": {"accommodations_booked": 51, "revenue": 1929.09}, "2025-10-12": {"accommodations_booked": 47, "revenue": 1605.0100000000002}, "2025-10-13": {"accommodations_booked": 48, "revenue": 1700.4599999999996}, "2025-10-14": {"accommodations_booked": 46, "revenue": 1670.1200000000001}, "2025-10-15": {"accommodations_booked": 43, "revenue": 1584.0700000000002}, "2025-10-16": {"accommodations_booked": 40, "revenue": 1483.2599999999995}, "2025-10-17": {"accommodations_booked": 52, "revenue": 1999.4099999999996}, "2025-10-18": {"accommodations_booked": 45, "revenue": 1740.7099999999996}, "2025-10-19": {"accommodations_booked": 35, "revenue": 1293.84}, "2025-10-20": {"accommodations_booked": 34, "revenue": 1215.2599999999998}, "2025-10-21": {"accommodations_booked": 34, "revenue": 1286.8799999999997}, "2025-10-22": {"accommodations_booked": 37, "revenue": 1363.1}, "2025-10-23": {"accommodations_booked": 34, "revenue": 1239.97}, "2025-10-24": {"accommodations_booked": 41, "revenue": 1507.5499999999997}, "2025-10-25": {"accommodations_booked": 40, "revenue": 1590.4800000000002}, "2025-10-26": {"accommodations_booked": 38, "revenue": 1435.1200000000001}, "2025-10-27": {"accommodations_booked": 37, "revenue": 1368.6100000000001}, "2025-10-28": {"accommodations_booked": 40, "revenue": 1517.95}, "2025-10-29": {"accommodations_booked": 46, "revenue": 1657.74}, "2025-10-30": {"accommodations_booked": 62, "revenue": 2218.74}, "2025-10-31": {"accommodations_booked": 68, "revenue": 2527.05}, "2025-11-01": {"accommodations_booked": 70, "revenue": 2592.529999999999}, "2025-11-02": {"accommodations_booked": 64, "revenue": 2402.6000000000004}, "2025-11-03": {"accommodations_booked": 64, "revenue": 2413.84}, "2025-11-04": {"accommodations_booked": 63, "revenue": 2331.560000000001}, "2025-11-05": {"accommodations_booked": 54, "revenue": 1876.5599999999995}, "2025-11-06": {"accommodations_booked": 63, "revenue": 2230.4300000000003}, "2025-11-07": {"accommodations_booked": 66, "revenue": 2440.9399999999996}, "2025-11-08": {"accommodations_booked": 69, "revenue": 2631.6400000000003}, "2025-11-09": {"accommodations_booked": 64, "revenue": 2277.8899999999994}, "2025-11-10": {"accommodations_booked": 57, "revenue": 2135.35}, "2025-11-11": {"accommodations_booked": 54, "revenue": 1994.6999999999998}, "2025-11-12": {"accommodations_booked": 58, "revenue": 2181.879999999999}, "2025-11-13": {"accommodations_booked": 59, "revenue": 2195.16}, "2025-11-14": {"accommodations_booked": 61, "revenue": 2393.1799999999994}, "2025-11-15": {"accommodations_booked": 68, "revenue": 2704.9200000000005}, "2025-11-16": {"accommodations_booked": 66, "revenue": 2569.130000000001}, "2025-11-17": {"accommodations_booked": 59, "revenue": 2243.8899999999994}, "2025-11-18": {"accommodations_booked": 60, "revenue": 2254.0600000000004}, "2025-11-19": {"accommodations_booked": 64, "revenue": 2509.6800000000003}, "2025-11-20": {"accommodations_booked": 68, "revenue": 2638.85}, "2025-11-21": {"accommodations_booked": 68, "revenue": 2532.37}, "2025-11-22": {"accommodations_booked": 68, "revenue": 2489.7299999999996}, "2025-11-23": {"accommodations_booked": 69, "revenue": 2467.8499999999995}, "2025-11-24": {"accommodations_booked": 68, "revenue": 2406.47}, "2025-11-25": {"accommodations_booked": 67, "revenue": 2401.2599999999993}, "2025-11-26": {"accommodations_booked": 61, "revenue": 2158.269999999999}, "2025-11-27": {"accommodations_booked": 64, "revenue": 2416.9199999999996}, "2025-11-28": {"accommodations_booked": 66, "revenue": 2549.16}, "2025-11-29": {"accommodations_booked": 71, "revenue": 2861.830000000001}, "2025-11-30": {"accommodations_booked": 62, "revenue": 2179.989999999999}, "2025-12-01": {"accommodations_booked": 58, "revenue": 2505.4400000000005}, "2025-12-02": {"accommodations_booked": 58, "revenue": 2378.1600000000003}, "2025-12-03": {"accommodations_booked": 66, "revenue": 2603.78}, "2025-12-04": {"accommodations_booked": 66, "revenue": 2678.75}, "2025-12-05": {"accommodations_booked": 71, "revenue": 3322.510000000001}, "2025-12-06": {"accommodations_booked": 72, "revenue": 3246.99}, "2025-12-07": {"accommodations_booked": 63, "revenue": 2549.18}, "2025-12-08": {"accommodations_booked": 54, "revenue": 2014.6799999999992}, "2025-12-09": {"accommodations_booked": 50, "revenue": 1925.8799999999999}, "2025-12-10": {"accommodations_booked": 51, "revenue": 1927.8699999999997}, "2025-12-11": {"accommodations_booked": 52, "revenue": 1961.78}, "2025-12-12": {"accommodations_booked": 57, "revenue": 2275.03}, "2025-12-13": {"accommodations_booked": 62, "revenue": 2586.7899999999995}, "2025-12-14": {"accommodations_booked": 52, "revenue": 1933.5699999999993}, "2025-12-15": {"accommodations_booked": 42, "revenue": 1577.36}, "2025-12-16": {"accommodations_booked": 41, "revenue": 1584.17}, "2025-12-17": {"accommodations_booked": 39, "revenue": 1543.6599999999999}, "2025-12-18": {"accommodations_booked": 35, "revenue": 1320.83}, "2025-12-19": {"accommodations_booked": 38, "revenue": 1455.3799999999999}, "2025-12-20": {"accommodations_booked": 40, "revenue": 1473.3999999999999}, "2025-12-21": {"accommodations_booked": 43, "revenue": 1545.4999999999998}, "2025-12-22": {"accommodations_booked": 49, "revenue": 2030.1299999999994}, "2025-12-23": {"accommodations_booked": 46, "revenue": 1883.9499999999998}, "2025-12-24": {"accommodations_booked": 58, "revenue": 2497.7099999999996}, "2025-12-25": {"accommodations_booked": 67, "revenue": 2912.0800000000013}, "2025-12-26": {"accommodations_booked": 78, "revenue": 3512.34}, "2025-12-27": {"accommodations_booked": 85, "revenue": 4115.870000000003}, "2025-12-28": {"accommodations_booked": 74, "revenue": 3131.869999999999}, "2025-12-29": {"accommodations_booked": 62, "revenue": 2480.9300000000003}, "2025-12-30": {"accommodations_booked": 66, "revenue": 2639.02}, "2025-12-31": {"accommodations_booked": 84, "revenue": 3756.8400000000015}}, "monthly_checkins": {"1": 538, "2": 344, "3": 583, "4": 279, "5": 143, "6": 128, "7": 160, "8": 134, "9": 125, "10": 250, "11": 343, "12": 340}}